empresa4/__init__.py
empresa4/core.py
empresa4/dtw.py
empresa4/dtw2.py
empresa4/datasets/02_sellout_agrupado_por_cliente.csv
empresa4/datasets/03_make_datasets_clase_2_with_FE.ipynb
empresa4/datasets/__init__.py
empresa4/datasets/maestro_productos.csv
empresa4/datasets/mejores_clientes.csv
empresa4/datasets/mejores_productos.csv
empresa4/datasets/tb_sellout_01_120.csv
empresa4/datasets/tb_sellout_01_original.csv
empresa4/datasets/tb_sellout_01_producto_estrella.csv
empresa4/datasets/tb_sellout_01_productos_todos.csv
empresa4/datasets/tb_sellout_02_120.csv
empresa4/datasets/tb_sellout_02_120_anti_leak.csv
empresa4/datasets/tb_sellout_02_original.csv
empresa4/datasets/tb_sellout_02_precios_cuidados.csv
empresa4/datasets/tb_sellout_02_producto_estrella.csv
empresa4/datasets/tb_sellout_02_productos_todos.csv
empresa4/datasets/tb_sellout_02_productos_todos_anti_leak.csv
empresa4/datasets/tb_sellout_02_productos_todos_con_FE_04.csv
empresa4/datasets/tb_sellout_02_productos_todos_con_FE_06.csv
empresa4/datasets/tb_stocks_02_productos_todos.csv
empresa4/datasets/tb_stocks_02_productos_todos_anti_leak.csv
empresa4/datasets/test.ipynb
empresa4/datasets/test.py
empresa4/datasets/time_series_dataset.csv
empresa4-2.0.6.dist-info/LICENSE.txt
empresa4-2.0.6.dist-info/METADATA
empresa4-2.0.6.dist-info/WHEEL
empresa4-2.0.6.dist-info/top_level.txt
empresa4-2.0.6.dist-info/RECORD
