Metadata-Version: 2.1
Name: empresa4
Version: 2.0.6
Summary: Empresa 4 Library for Laboratorio de Implementación 3
Author: Gero
Author-email: geropellicer@gmail.com
License-File: LICENSE.txt
Requires-Dist: pandas
Requires-Dist: numpy
Requires-Dist: scipy
Requires-Dist: pytest
